{
  "centreData": [
    {
      "id": "MC001",
      "regNo": "123456",
      "name": "Medicare Pvt Ltd",
      "address": "Pannipitiya",
      "town": "Pannipitiya",
      "phone": "011-1234567",
      "email": "medicare@gmail.com"
    },
    {
      "id": "MC002",
      "regNo": "123457",
      "name": "Chapa Medical Centre",
      "address": "Nugegoda",
      "town": "Nugegoda",
      "phone": "011-1234567",
      "email": "chapa@gmail.com"
    }
  ],
  "roleData": [
    {
      "id": "R001",
      "name": "Admin Doctor"
    },
    {
      "id": "R002",
      "name": "Doctor"
    },
    {
      "id": "R003",
      "name": "Medical Assistant"
    }
  ]
}
